ztask.py
ztask-0.1.5.dist-info/entry_points.txt
ztask-0.1.5.dist-info/WHEEL
ztask-0.1.5.dist-info/METADATA
ztask-0.1.5.dist-info/RECORD
