Metadata-Version: 2.1
Name: ztask
Version: 0.1.5
Summary: Ztask, the terminal interface to log task in zohoprojects and complete the damned timesheets with a Taskwarrior inspired syntax.
Home-page: https://github.com/PabloRuizCuevas/ztask
License: GPLv2
Author: Pablo Ruiz
Requires-Python: >=3.8,<4.0
Classifier: License :: Other/Proprietary License
Classifier: Programming Language :: Python :: 3
Classifier: Programming Language :: Python :: 3.10
Classifier: Programming Language :: Python :: 3.8
Classifier: Programming Language :: Python :: 3.9
Requires-Dist: pandas (>=1.3.5,<2.0.0)
Requires-Dist: parsedatetime (>=2.6,<3.0)
Requires-Dist: prettytable (>=3.0.0,<4.0.0)
